tools/__init__.py
tools/genlogs.py
watchl/__init__.py
watchl/config.py
watchl/defaults.py
watchl/main.py
watchl/py.typed
watchl/utils.py
watchl/models/__init__.py
watchl/models/alerts.py
watchl/models/logs.py
watchl/models/metrics.py
watchl/models/quantities.py
watchl-0.2.dist-info/LICENSE
watchl-0.2.dist-info/METADATA
watchl-0.2.dist-info/WHEEL
watchl-0.2.dist-info/entry_points.txt
watchl-0.2.dist-info/top_level.txt
watchl-0.2.dist-info/RECORD
