Metadata-Version: 2.1
Name: watchl
Version: 0.2
Summary: Lightweight HTTP log monitoring and alerting tool
Home-page: https://github.com/florimondmanca/watchl.git
Author: Florimond Manca
Author-email: florimond.manca@gmail.com
License: MIT
Platform: UNKNOWN
Classifier: Development Status :: 3 - Alpha
Classifier: Intended Audience :: Developers
Classifier: License :: OSI Approved :: MIT License
Classifier: Operating System :: OS Independent
Classifier: Programming Language :: Python
Classifier: Programming Language :: Python :: 3
Classifier: Programming Language :: Python :: 3 :: Only
Classifier: Programming Language :: Python :: 3.6
Classifier: Programming Language :: Python :: 3.7
Requires-Python: >=3.6
Requires-Dist: trio (<0.13,>=0.12)
Requires-Dist: click (<8,>=7)
Requires-Dist: python-json-logger
Provides-Extra: dev
Requires-Dist: pytest ; extra == 'dev'
Requires-Dist: pytest-cov ; extra == 'dev'
Requires-Dist: codecov ; extra == 'dev'
Requires-Dist: black ; extra == 'dev'
Requires-Dist: pylint ; extra == 'dev'
Requires-Dist: rope ; extra == 'dev'
Requires-Dist: mypy ; extra == 'dev'
